MANIFEST.in
README.txt
setup.cfg
setup.py
docs/HISTORY.txt
docs/INSTALL.txt
docs/LICENSE.GPL
docs/LICENSE.txt
jalonedit/__init__.py
jalonedit.content.egg-info/PKG-INFO
jalonedit.content.egg-info/SOURCES.txt
jalonedit.content.egg-info/dependency_links.txt
jalonedit.content.egg-info/entry_points.txt
jalonedit.content.egg-info/namespace_packages.txt
jalonedit.content.egg-info/not-zip-safe
jalonedit.content.egg-info/paster_plugins.txt
jalonedit.content.egg-info/requires.txt
jalonedit.content.egg-info/top_level.txt
jalonedit/content/README.txt
jalonedit/content/__init__.py
jalonedit/content/config.py
jalonedit/content/configure.zcml
jalonedit/content/skins.zcml
jalonedit/content/browser/__init__.py
jalonedit/content/browser/configure.zcml
jalonedit/content/browser/scripts/__init__.py
jalonedit/content/browser/scripts/presentation.py
jalonedit/content/browser/scripts/ressource.py
jalonedit/content/browser/templates/blocPresentation_view.pt
jalonedit/content/browser/templates/documentSemantique_collage.pt
jalonedit/content/browser/templates/documentSemantique_view.pt
jalonedit/content/browser/templates/presentation_view.pt
jalonedit/content/browser/templates/ressource_view.pt
jalonedit/content/browser/templates/video_collage.pt
jalonedit/content/browser/templates/video_view.pt
jalonedit/content/content/__init__.py
jalonedit/content/content/bibliographie.py
jalonedit/content/content/blocPresentation.py
jalonedit/content/content/configure.zcml
jalonedit/content/content/documentSemantique.py
jalonedit/content/content/glossaire.py
jalonedit/content/content/video.py
jalonedit/content/interfaces/__init__.py
jalonedit/content/interfaces/jaloneditinterface.py
jalonedit/content/profiles/default/actions.xml
jalonedit/content/profiles/default/factorytool.xml
jalonedit/content/profiles/default/metadata.xml
jalonedit/content/profiles/default/propertiestool.xml
jalonedit/content/profiles/default/skins.xml
jalonedit/content/profiles/default/tinymce.xml
jalonedit/content/profiles/default/types.xml
jalonedit/content/profiles/default/types/Bibliographie.xml
jalonedit/content/profiles/default/types/BlocPresentation.xml
jalonedit/content/profiles/default/types/Collage.xml
jalonedit/content/profiles/default/types/DocumentSemantique.xml
jalonedit/content/profiles/default/types/Glossaire.xml
jalonedit/content/profiles/default/types/Video.xml
